LICENSE
MANIFEST.in
README.rst
setup.cfg
setup.py
dtool_lookup_server/__init__.py
dtool_lookup_server/base_uri_routes.py
dtool_lookup_server/cli.py
dtool_lookup_server/config.py
dtool_lookup_server/config_routes.py
dtool_lookup_server/dataset_routes.py
dtool_lookup_server/date_utils.py
dtool_lookup_server/extensions.py
dtool_lookup_server/permission_routes.py
dtool_lookup_server/schemas.py
dtool_lookup_server/sql_models.py
dtool_lookup_server/user_admin_routes.py
dtool_lookup_server/user_routes.py
dtool_lookup_server/utils.py
dtool_lookup_server/utils_auth.py
dtool_lookup_server.egg-info/PKG-INFO
dtool_lookup_server.egg-info/SOURCES.txt
dtool_lookup_server.egg-info/dependency_links.txt
dtool_lookup_server.egg-info/entry_points.txt
dtool_lookup_server.egg-info/requires.txt
dtool_lookup_server.egg-info/top_level.txt
dtool_lookup_server/templates/index.html
tests/test_admin_user_routes.py
tests/test_base_uri_routes.py
tests/test_cli.py
tests/test_config.py
tests/test_config_routes.py
tests/test_dataset_routes.py
tests/test_lookup_datasets_by_user_and_uuid.py
tests/test_permission_routes.py
tests/test_sql_dataset_utils.py
tests/test_sql_list_datasets_by_user.py
tests/test_summary_of_datasets_by_user.py
tests/test_timestamp_consistency.py
tests/test_user_routes.py
tests/test_utils.py
tests/test_utils_auth.py
tests/test_utils_base_uri_management.py
tests/test_utils_dataset_info_is_valid.py
tests/test_utils_get_annotations_from_uri_by_user.py
tests/test_utils_get_manifest_from_uri_by_user.py
tests/test_utils_get_readme_from_uri_by_user.py
tests/test_utils_permission_management.py
tests/test_utils_preprocess_query_base_uris.py
tests/test_utils_register_dataset.py
tests/test_utils_user_management.py