Metadata-Version: 2.1
Name: dtool-lookup-server
Version: 0.18.0
Summary: Web API to register/lookup/search for dtool dataset metadata
Home-page: https://github.com/jic-dtool/dtool-lookup-server
Download-URL: https://github.com/jic-dtool/dtool-lookup-server/tarball/0.18.0
Author: Tjelvar Olsson
Author-email: tjelvar.olsson@gmail.com
License: MIT
License-File: LICENSE
